waku/__init__.py
waku/application.py
waku/cqrs/__init__.py
waku/cqrs/contracts/__init__.py
waku/cqrs/contracts/event.py
waku/cqrs/contracts/notification.py
waku/cqrs/contracts/pipeline.py
waku/cqrs/contracts/request.py
waku/cqrs/events/__init__.py
waku/cqrs/events/handler.py
waku/cqrs/events/map.py
waku/cqrs/events/publish.py
waku/cqrs/exceptions.py
waku/cqrs/impl.py
waku/cqrs/interfaces.py
waku/cqrs/modules.py
waku/cqrs/pipeline/__init__.py
waku/cqrs/pipeline/chain.py
waku/cqrs/pipeline/map.py
waku/cqrs/requests/__init__.py
waku/cqrs/requests/handler.py
waku/cqrs/requests/map.py
waku/cqrs/utils.py
waku/di/__init__.py
waku/di/_activation.py
waku/di/_providers.py
waku/exceptions.py
waku/extensions/__init__.py
waku/extensions/protocols.py
waku/extensions/registry.py
waku/factory.py
waku/lifespan.py
waku/modules/__init__.py
waku/modules/_metadata.py
waku/modules/_metadata_registry.py
waku/modules/_module.py
waku/modules/_registry.py
waku/modules/_registry_builder.py
waku/py.typed
waku/testing.py
waku/validation/__init__.py
waku/validation/_abc.py
waku/validation/_errors.py
waku/validation/_extension.py
waku/validation/rules/__init__.py
waku/validation/rules/_cache.py
waku/validation/rules/_types_extractor.py
waku/validation/rules/dependency_accessible.py
waku-0.27.0.dist-info/WHEEL
waku-0.27.0.dist-info/METADATA
waku-0.27.0.dist-info/RECORD
