Metadata-Version: 2.4
Name: waku
Version: 0.27.0
Summary: Framework for building modular and loosely coupled applications
Keywords: architecture,modular,decoupled,framework,dishka,ioc,di
Author: Daniil Kharkov, Doctor
Author-email: Daniil Kharkov <fadeddexofan@gmail.com>, Doctor <thirvondukr@gmail.com>
License-Expression: MIT
Classifier: Development Status :: 3 - Alpha
Classifier: Intended Audience :: Developers
Classifier: License :: OSI Approved :: MIT License
Classifier: Operating System :: OS Independent
Classifier: Programming Language :: Python
Classifier: Programming Language :: Python :: 3 :: Only
Classifier: Programming Language :: Python :: 3.11
Classifier: Programming Language :: Python :: 3.12
Classifier: Programming Language :: Python :: 3.13
Classifier: Programming Language :: Python :: 3.14
Classifier: Topic :: Software Development :: Libraries
Classifier: Topic :: Software Development :: Libraries :: Application Frameworks
Classifier: Typing :: Typed
Requires-Dist: anyio>=4.7.0
Requires-Dist: dishka>=1.6.0
Requires-Dist: typing-extensions>=4.12.2
Requires-Python: >=3.11
Project-URL: Changelog, https://github.com/waku-py/waku/blob/master/CHANGELOG.md
Project-URL: Documentation, https://waku-py.github.io/waku/
Project-URL: Issues, https://github.com/waku-py/waku/issues
Project-URL: Repository, https://github.com/waku-py/waku
